console_chess_imandyr/__init__.py
console_chess_imandyr/base.py
console_chess_imandyr/bot.py
console_chess_imandyr/figures.py
console_chess_imandyr/game.py
console_chess_imandyr/tests/__init__.py
console_chess_imandyr/tests/test.py
console_chess_imandyr-1.6.5.dist-info/METADATA
console_chess_imandyr-1.6.5.dist-info/WHEEL
console_chess_imandyr-1.6.5.dist-info/licenses/LICENSE
console_chess_imandyr-1.6.5.dist-info/RECORD
