Metadata-Version: 2.1
Name: console_chess_imandyr
Version: 1.6.5
Summary: Implementation of chess game which can be played through console.
Project-URL: Homepage, https://github.com/Imandyr/Console-Chess
Project-URL: Issues, https://github.com/Imandyr/Console-Chess/issues
Author-email: Imandyr <imandyremail@gmail.com>
License-File: LICENSE
Classifier: License :: OSI Approved :: MIT License
Classifier: Operating System :: OS Independent
Classifier: Programming Language :: Python :: 3
Requires-Python: >=3.10
